CleanerVersion-2.0.0.dist-info/DESCRIPTION.rst
CleanerVersion-2.0.0.dist-info/METADATA
CleanerVersion-2.0.0.dist-info/RECORD
CleanerVersion-2.0.0.dist-info/WHEEL
CleanerVersion-2.0.0.dist-info/metadata.json
CleanerVersion-2.0.0.dist-info/top_level.txt
cleanerversion/__init__.py
cleanerversion/urls.py
cleanerversion/settings/__init__.py
cleanerversion/settings/base.py
cleanerversion/settings/pg.py
cleanerversion/settings/pg_travis.py
cleanerversion/settings/sqlite.py
versions/__init__.py
versions/admin.py
versions/deletion.py
versions/descriptors.py
versions/exceptions.py
versions/fields.py
versions/models.py
versions/settings.py
versions/static/js/admin_addon.js
versions/templates/versions/datetimefilter.html
versions/util/__init__.py
versions/util/helper.py
versions/util/postgresql.py
versions_tests/__init__.py
versions_tests/admin.py
versions_tests/apps.py
versions_tests/models.py
versions_tests/tests/__init__.py
versions_tests/tests/test_commands.py
versions_tests/tests/test_models.py
versions_tests/tests/test_utils.py
