Metadata-Version: 2.0
Name: CleanerVersion
Version: 2.0.0
Summary: A versioning solution for relational data models using the Django ORM
Home-page: https://github.com/swisscom/cleanerversion
Author: Manuel Jeckelmann, Jean-Christophe Zulian, Brian King, Andrea Marcacci
Author-email: engineering.sophia@swisscom.com
License: Apache License 2.0
Platform: UNKNOWN
Classifier: Development Status :: 5 - Production/Stable
Classifier: Framework :: Django
Classifier: Intended Audience :: Developers
Classifier: Programming Language :: Python :: 2.7
Classifier: Programming Language :: Python :: 3.6
Classifier: Topic :: Database
Classifier: Topic :: System :: Archiving
Requires-Dist: django
